{
  "date": "20251130",
  "games": [
    {
      "game_id": "handball4all.baden-wuerttemberg.8666306",
      "order": 38,
      "date": "So, 30.11.",
      "home": {
        "team_name": "Team Stuttgart",
        "players": [
          {
            "name": "Leonard Blum",
            "goals": 3,
            "two_min_penalties": 0,
            "yellow_cards": 0,
            "red_cards": 0,
            "blue_cards": 0,
            "seven_meters": 0,
            "seven_meters_goals": 0
          },
          {
            "name": "Hugo Frech",
            "goals": 5,
            "two_min_penalties": 0,
            "yellow_cards": 0,
            "red_cards": 0,
            "blue_cards": 0,
            "seven_meters": 0,
            "seven_meters_goals": 0
          },
          {
            "name": "Lasse Dalferth",
            "goals": 0,
            "two_min_penalties": 0,
            "yellow_cards": 0,
            "red_cards": 0,
            "blue_cards": 0,
            "seven_meters": 0,
            "seven_meters_goals": 0
          },
          {
            "name": "David Bieler",
            "goals": 1,
            "two_min_penalties": 0,
            "yellow_cards": 0,
            "red_cards": 0,
            "blue_cards": 0,
            "seven_meters": 0,
            "seven_meters_goals": 0
          },
          {
            "name": "Samuel Schlumberger-Ruiz",
            "goals": 1,
            "two_min_penalties": 0,
            "yellow_cards": 0,
            "red_cards": 0,
            "blue_cards": 0,
            "seven_meters": 0,
            "seven_meters_goals": 0
          },
          {
            "name": "Yann Ettling",
            "goals": 1,
            "two_min_penalties": 0,
            "yellow_cards": 0,
            "red_cards": 0,
            "blue_cards": 0,
            "seven_meters": 0,
            "seven_meters_goals": 0
          },
          {
            "name": "Enric Pena Brossa",
            "goals": 4,
            "two_min_penalties": 0,
            "yellow_cards": 0,
            "red_cards": 0,
            "blue_cards": 0,
            "seven_meters": 0,
            "seven_meters_goals": 0
          },
          {
            "name": "Adrian Zoric",
            "goals": 3,
            "two_min_penalties": 0,
            "yellow_cards": 0,
            "red_cards": 0,
            "blue_cards": 0,
            "seven_meters": 2,
            "seven_meters_goals": 2
          },
          {
            "name": "Florian Leuze",
            "goals": 1,
            "two_min_penalties": 0,
            "yellow_cards": 0,
            "red_cards": 0,
            "blue_cards": 0,
            "seven_meters": 0,
            "seven_meters_goals": 0
          },
          {
            "name": "Jakob Baisch",
            "goals": 5,
            "two_min_penalties": 0,
            "yellow_cards": 0,
            "red_cards": 0,
            "blue_cards": 0,
            "seven_meters": 0,
            "seven_meters_goals": 0
          },
          {
            "name": "Florian R\u00f6hl",
            "goals": 0,
            "two_min_penalties": 0,
            "yellow_cards": 0,
            "red_cards": 0,
            "blue_cards": 0,
            "seven_meters": 0,
            "seven_meters_goals": 0
          },
          {
            "name": "Samuel Birkle",
            "goals": 9,
            "two_min_penalties": 0,
            "yellow_cards": 0,
            "red_cards": 0,
            "blue_cards": 0,
            "seven_meters": 4,
            "seven_meters_goals": 4
          },
          {
            "name": "Lino Herz",
            "goals": 4,
            "two_min_penalties": 0,
            "yellow_cards": 0,
            "red_cards": 0,
            "blue_cards": 0,
            "seven_meters": 0,
            "seven_meters_goals": 0
          }
        ]
      },
      "away": {
        "team_name": "TSV K\u00f6ngen",
        "players": [
          {
            "name": "Felix Rosen\u00e4cker",
            "goals": 1,
            "two_min_penalties": 0,
            "yellow_cards": 0,
            "red_cards": 0,
            "blue_cards": 0,
            "seven_meters": 0,
            "seven_meters_goals": 0
          },
          {
            "name": "Mats Sch\u00f6ll",
            "goals": 1,
            "two_min_penalties": 0,
            "yellow_cards": 1,
            "red_cards": 0,
            "blue_cards": 0,
            "seven_meters": 0,
            "seven_meters_goals": 0
          },
          {
            "name": "Theo Sterr",
            "goals": 2,
            "two_min_penalties": 0,
            "yellow_cards": 0,
            "red_cards": 0,
            "blue_cards": 0,
            "seven_meters": 0,
            "seven_meters_goals": 0
          },
          {
            "name": "Malte Lentzen",
            "goals": 2,
            "two_min_penalties": 1,
            "yellow_cards": 0,
            "red_cards": 0,
            "blue_cards": 0,
            "seven_meters": 0,
            "seven_meters_goals": 0
          },
          {
            "name": "Marian Siegel",
            "goals": 9,
            "two_min_penalties": 1,
            "yellow_cards": 0,
            "red_cards": 0,
            "blue_cards": 0,
            "seven_meters": 1,
            "seven_meters_goals": 1
          },
          {
            "name": "Leon Winterling",
            "goals": 0,
            "two_min_penalties": 0,
            "yellow_cards": 0,
            "red_cards": 0,
            "blue_cards": 0,
            "seven_meters": 0,
            "seven_meters_goals": 0
          },
          {
            "name": "Tristan Paul Hurst",
            "goals": 1,
            "two_min_penalties": 0,
            "yellow_cards": 0,
            "red_cards": 0,
            "blue_cards": 0,
            "seven_meters": 0,
            "seven_meters_goals": 0
          },
          {
            "name": "Kai Breuer",
            "goals": 0,
            "two_min_penalties": 0,
            "yellow_cards": 0,
            "red_cards": 0,
            "blue_cards": 0,
            "seven_meters": 0,
            "seven_meters_goals": 0
          },
          {
            "name": "Tobias Schnaidt",
            "goals": 0,
            "two_min_penalties": 0,
            "yellow_cards": 0,
            "red_cards": 0,
            "blue_cards": 0,
            "seven_meters": 0,
            "seven_meters_goals": 0
          },
          {
            "name": "Jannik Ziegler",
            "goals": 3,
            "two_min_penalties": 0,
            "yellow_cards": 0,
            "red_cards": 0,
            "blue_cards": 0,
            "seven_meters": 1,
            "seven_meters_goals": 0
          },
          {
            "name": "Jakob Pajonczyk",
            "goals": 9,
            "two_min_penalties": 1,
            "yellow_cards": 0,
            "red_cards": 0,
            "blue_cards": 0,
            "seven_meters": 0,
            "seven_meters_goals": 0
          },
          {
            "name": "Niklas T\u00f6pler",
            "goals": 0,
            "two_min_penalties": 0,
            "yellow_cards": 0,
            "red_cards": 0,
            "blue_cards": 0,
            "seven_meters": 0,
            "seven_meters_goals": 0
          }
        ]
      },
      "goals_timeline": [
        {
          "minute": 1,
          "second": 21,
          "scorer": "Jakob Pajonczyk",
          "team": "home",
          "team_abbrev": "TSV K\u00f6ngen",
          "seven_meter": false
        },
        {
          "minute": 1,
          "second": 48,
          "scorer": "Samuel Birkle",
          "team": "away",
          "team_abbrev": "Team Stuttgart",
          "seven_meter": false
        },
        {
          "minute": 2,
          "second": 20,
          "scorer": "Jakob Pajonczyk",
          "team": "home",
          "team_abbrev": "TSV K\u00f6ngen",
          "seven_meter": false
        },
        {
          "minute": 3,
          "second": 27,
          "scorer": "Samuel Birkle",
          "team": "away",
          "team_abbrev": "Team Stuttgart",
          "seven_meter": true
        },
        {
          "minute": 5,
          "second": 2,
          "scorer": "Marian Siegel",
          "team": "home",
          "team_abbrev": "TSV K\u00f6ngen",
          "seven_meter": false
        },
        {
          "minute": 6,
          "second": 25,
          "scorer": "Marian Siegel",
          "team": "home",
          "team_abbrev": "TSV K\u00f6ngen",
          "seven_meter": false
        },
        {
          "minute": 8,
          "second": 17,
          "scorer": "Jakob Pajonczyk",
          "team": "home",
          "team_abbrev": "TSV K\u00f6ngen",
          "seven_meter": false
        },
        {
          "minute": 9,
          "second": 55,
          "scorer": "Malte Lentzen",
          "team": "home",
          "team_abbrev": "TSV K\u00f6ngen",
          "seven_meter": false
        },
        {
          "minute": 10,
          "second": 37,
          "scorer": "Marian Siegel",
          "team": "home",
          "team_abbrev": "TSV K\u00f6ngen",
          "seven_meter": false
        },
        {
          "minute": 10,
          "second": 49,
          "scorer": "Leonard Blum",
          "team": "away",
          "team_abbrev": "Team Stuttgart",
          "seven_meter": false
        },
        {
          "minute": 11,
          "second": 30,
          "scorer": "Jakob Pajonczyk",
          "team": "home",
          "team_abbrev": "TSV K\u00f6ngen",
          "seven_meter": false
        },
        {
          "minute": 11,
          "second": 55,
          "scorer": "Hugo Frech",
          "team": "away",
          "team_abbrev": "Team Stuttgart",
          "seven_meter": false
        },
        {
          "minute": 12,
          "second": 25,
          "scorer": "Jakob Baisch",
          "team": "away",
          "team_abbrev": "Team Stuttgart",
          "seven_meter": false
        },
        {
          "minute": 13,
          "second": 28,
          "scorer": "Malte Lentzen",
          "team": "home",
          "team_abbrev": "TSV K\u00f6ngen",
          "seven_meter": false
        },
        {
          "minute": 13,
          "second": 43,
          "scorer": "Jakob Baisch",
          "team": "away",
          "team_abbrev": "Team Stuttgart",
          "seven_meter": false
        },
        {
          "minute": 15,
          "second": 48,
          "scorer": "Samuel Birkle",
          "team": "away",
          "team_abbrev": "Team Stuttgart",
          "seven_meter": true
        },
        {
          "minute": 16,
          "second": 25,
          "scorer": "Tristan Hurst",
          "team": "home",
          "team_abbrev": "TSV K\u00f6ngen",
          "seven_meter": false
        },
        {
          "minute": 17,
          "second": 19,
          "scorer": "Marian Siegel",
          "team": "home",
          "team_abbrev": "TSV K\u00f6ngen",
          "seven_meter": false
        },
        {
          "minute": 17,
          "second": 27,
          "scorer": "Enric Pena Brossa",
          "team": "away",
          "team_abbrev": "Team Stuttgart",
          "seven_meter": false
        },
        {
          "minute": 18,
          "second": 8,
          "scorer": "Jakob Pajonczyk",
          "team": "home",
          "team_abbrev": "TSV K\u00f6ngen",
          "seven_meter": false
        },
        {
          "minute": 18,
          "second": 46,
          "scorer": "Hugo Frech",
          "team": "away",
          "team_abbrev": "Team Stuttgart",
          "seven_meter": false
        },
        {
          "minute": 19,
          "second": 37,
          "scorer": "Enric Pena Brossa",
          "team": "away",
          "team_abbrev": "Team Stuttgart",
          "seven_meter": true
        },
        {
          "minute": 20,
          "second": 4,
          "scorer": "Marian Siegel",
          "team": "home",
          "team_abbrev": "TSV K\u00f6ngen",
          "seven_meter": false
        },
        {
          "minute": 20,
          "second": 14,
          "scorer": "Marian Siegel",
          "team": "home",
          "team_abbrev": "TSV K\u00f6ngen",
          "seven_meter": false
        },
        {
          "minute": 20,
          "second": 25,
          "scorer": "Lino Herz",
          "team": "away",
          "team_abbrev": "Team Stuttgart",
          "seven_meter": false
        },
        {
          "minute": 21,
          "second": 8,
          "scorer": "Mats Sch\u00f6ll",
          "team": "home",
          "team_abbrev": "TSV K\u00f6ngen",
          "seven_meter": false
        },
        {
          "minute": 21,
          "second": 48,
          "scorer": "Enric Pena Brossa",
          "team": "away",
          "team_abbrev": "Team Stuttgart",
          "seven_meter": false
        },
        {
          "minute": 22,
          "second": 12,
          "scorer": "Marian Siegel",
          "team": "home",
          "team_abbrev": "TSV K\u00f6ngen",
          "seven_meter": false
        },
        {
          "minute": 22,
          "second": 33,
          "scorer": "Theo Sterr",
          "team": "home",
          "team_abbrev": "TSV K\u00f6ngen",
          "seven_meter": false
        },
        {
          "minute": 23,
          "second": 39,
          "scorer": "Lino Herz",
          "team": "away",
          "team_abbrev": "Team Stuttgart",
          "seven_meter": false
        },
        {
          "minute": 24,
          "second": 18,
          "scorer": "Enric Pena Brossa",
          "team": "away",
          "team_abbrev": "Team Stuttgart",
          "seven_meter": false
        },
        {
          "minute": 25,
          "second": 23,
          "scorer": "Jakob Baisch",
          "team": "away",
          "team_abbrev": "Team Stuttgart",
          "seven_meter": false
        },
        {
          "minute": 25,
          "second": 59,
          "scorer": "Jakob Baisch",
          "team": "away",
          "team_abbrev": "Team Stuttgart",
          "seven_meter": false
        },
        {
          "minute": 26,
          "second": 39,
          "scorer": "Yann Ettling",
          "team": "away",
          "team_abbrev": "Team Stuttgart",
          "seven_meter": false
        },
        {
          "minute": 27,
          "second": 3,
          "scorer": "Marian Siegel",
          "team": "home",
          "team_abbrev": "TSV K\u00f6ngen",
          "seven_meter": false
        },
        {
          "minute": 27,
          "second": 33,
          "scorer": "Samuel Birkle",
          "team": "away",
          "team_abbrev": "Team Stuttgart",
          "seven_meter": true
        },
        {
          "minute": 28,
          "second": 10,
          "scorer": "Jannik Ziegler",
          "team": "home",
          "team_abbrev": "TSV K\u00f6ngen",
          "seven_meter": false
        },
        {
          "minute": 28,
          "second": 24,
          "scorer": "Lino Herz",
          "team": "away",
          "team_abbrev": "Team Stuttgart",
          "seven_meter": false
        },
        {
          "minute": 30,
          "second": 39,
          "scorer": "Jakob Pajonczyk",
          "team": "home",
          "team_abbrev": "TSV K\u00f6ngen",
          "seven_meter": false
        },
        {
          "minute": 30,
          "second": 48,
          "scorer": "Samuel Birkle",
          "team": "away",
          "team_abbrev": "Team Stuttgart",
          "seven_meter": false
        },
        {
          "minute": 32,
          "second": 27,
          "scorer": "Lino Herz",
          "team": "away",
          "team_abbrev": "Team Stuttgart",
          "seven_meter": false
        },
        {
          "minute": 33,
          "second": 9,
          "scorer": "Theo Sterr",
          "team": "home",
          "team_abbrev": "TSV K\u00f6ngen",
          "seven_meter": false
        },
        {
          "minute": 34,
          "second": 17,
          "scorer": "Jakob Pajonczyk",
          "team": "home",
          "team_abbrev": "TSV K\u00f6ngen",
          "seven_meter": false
        },
        {
          "minute": 35,
          "second": 13,
          "scorer": "Samuel Birkle",
          "team": "away",
          "team_abbrev": "Team Stuttgart",
          "seven_meter": false
        },
        {
          "minute": 35,
          "second": 33,
          "scorer": "Jakob Pajonczyk",
          "team": "home",
          "team_abbrev": "TSV K\u00f6ngen",
          "seven_meter": false
        },
        {
          "minute": 36,
          "second": 6,
          "scorer": "Samuel Birkle",
          "team": "away",
          "team_abbrev": "Team Stuttgart",
          "seven_meter": true
        },
        {
          "minute": 36,
          "second": 37,
          "scorer": "Jakob Baisch",
          "team": "away",
          "team_abbrev": "Team Stuttgart",
          "seven_meter": false
        },
        {
          "minute": 36,
          "second": 59,
          "scorer": "Leonard Blum",
          "team": "away",
          "team_abbrev": "Team Stuttgart",
          "seven_meter": false
        },
        {
          "minute": 37,
          "second": 25,
          "scorer": "Samuel Birkle",
          "team": "away",
          "team_abbrev": "Team Stuttgart",
          "seven_meter": false
        },
        {
          "minute": 37,
          "second": 50,
          "scorer": "Felix Rosen\u00e4cker",
          "team": "home",
          "team_abbrev": "TSV K\u00f6ngen",
          "seven_meter": false
        },
        {
          "minute": 38,
          "second": 13,
          "scorer": "Samuel Birkle",
          "team": "away",
          "team_abbrev": "Team Stuttgart",
          "seven_meter": false
        },
        {
          "minute": 39,
          "second": 6,
          "scorer": "Adrian Zoric",
          "team": "away",
          "team_abbrev": "Team Stuttgart",
          "seven_meter": false
        },
        {
          "minute": 40,
          "second": 10,
          "scorer": "Jannik Ziegler",
          "team": "home",
          "team_abbrev": "TSV K\u00f6ngen",
          "seven_meter": false
        },
        {
          "minute": 41,
          "second": 52,
          "scorer": "Adrian Zoric",
          "team": "away",
          "team_abbrev": "Team Stuttgart",
          "seven_meter": true
        },
        {
          "minute": 42,
          "second": 26,
          "scorer": "David Bieler",
          "team": "away",
          "team_abbrev": "Team Stuttgart",
          "seven_meter": false
        },
        {
          "minute": 43,
          "second": 13,
          "scorer": "Adrian Zoric",
          "team": "away",
          "team_abbrev": "Team Stuttgart",
          "seven_meter": true
        },
        {
          "minute": 43,
          "second": 46,
          "scorer": "Hugo Frech",
          "team": "away",
          "team_abbrev": "Team Stuttgart",
          "seven_meter": false
        },
        {
          "minute": 45,
          "second": 21,
          "scorer": "Florian Leuze",
          "team": "away",
          "team_abbrev": "Team Stuttgart",
          "seven_meter": false
        },
        {
          "minute": 45,
          "second": 38,
          "scorer": "Marian Siegel",
          "team": "home",
          "team_abbrev": "TSV K\u00f6ngen",
          "seven_meter": true
        },
        {
          "minute": 46,
          "second": 1,
          "scorer": "Jakob Pajonczyk",
          "team": "home",
          "team_abbrev": "TSV K\u00f6ngen",
          "seven_meter": false
        },
        {
          "minute": 47,
          "second": 26,
          "scorer": "Hugo Frech",
          "team": "away",
          "team_abbrev": "Team Stuttgart",
          "seven_meter": false
        },
        {
          "minute": 48,
          "second": 52,
          "scorer": "Hugo Frech",
          "team": "away",
          "team_abbrev": "Team Stuttgart",
          "seven_meter": false
        },
        {
          "minute": 49,
          "second": 10,
          "scorer": "Leonard Blum",
          "team": "away",
          "team_abbrev": "Team Stuttgart",
          "seven_meter": false
        },
        {
          "minute": 49,
          "second": 41,
          "scorer": "Jannik Ziegler",
          "team": "home",
          "team_abbrev": "TSV K\u00f6ngen",
          "seven_meter": false
        }
      ],
      "final_score": "28:36",
      "half_duration": 30,
      "officials": {
        "referees": [
          "Jens-Ole Sommerkamp"
        ],
        "timekeepers": [
          "Uwe Bieler"
        ],
        "secretaries": [
          "Robert Siegel"
        ]
      },
      "graphic_path": "output/graphics/Team_Stuttgart_vs_TSV_K\u00f6ngen_So_3011.png"
    },
    {
      "game_id": "handball4all.baden-wuerttemberg.8666301",
      "order": 39,
      "date": "So, 30.11.",
      "home": {
        "team_name": "JSG Stuttgart Waldau",
        "players": [
          {
            "name": "Moritz Weber",
            "goals": 0,
            "two_min_penalties": 0,
            "yellow_cards": 0,
            "red_cards": 0,
            "blue_cards": 0,
            "seven_meters": 0,
            "seven_meters_goals": 0
          },
          {
            "name": "Tom Heldrich",
            "goals": 5,
            "two_min_penalties": 0,
            "yellow_cards": 0,
            "red_cards": 0,
            "blue_cards": 0,
            "seven_meters": 0,
            "seven_meters_goals": 0
          },
          {
            "name": "Paul Schoewe",
            "goals": 6,
            "two_min_penalties": 0,
            "yellow_cards": 1,
            "red_cards": 0,
            "blue_cards": 0,
            "seven_meters": 1,
            "seven_meters_goals": 1
          },
          {
            "name": "Elias B\u00fchler",
            "goals": 0,
            "two_min_penalties": 0,
            "yellow_cards": 0,
            "red_cards": 0,
            "blue_cards": 0,
            "seven_meters": 1,
            "seven_meters_goals": 0
          },
          {
            "name": "Adrian Hamm",
            "goals": 2,
            "two_min_penalties": 0,
            "yellow_cards": 0,
            "red_cards": 0,
            "blue_cards": 0,
            "seven_meters": 0,
            "seven_meters_goals": 0
          },
          {
            "name": "Lukas Spitznagel",
            "goals": 4,
            "two_min_penalties": 0,
            "yellow_cards": 0,
            "red_cards": 0,
            "blue_cards": 0,
            "seven_meters": 1,
            "seven_meters_goals": 1
          },
          {
            "name": "Jonathan Thriemer",
            "goals": 1,
            "two_min_penalties": 0,
            "yellow_cards": 0,
            "red_cards": 0,
            "blue_cards": 0,
            "seven_meters": 0,
            "seven_meters_goals": 0
          },
          {
            "name": "Theo Fetzer",
            "goals": 1,
            "two_min_penalties": 0,
            "yellow_cards": 0,
            "red_cards": 0,
            "blue_cards": 0,
            "seven_meters": 0,
            "seven_meters_goals": 0
          },
          {
            "name": "Oskar Eder",
            "goals": 11,
            "two_min_penalties": 0,
            "yellow_cards": 1,
            "red_cards": 0,
            "blue_cards": 0,
            "seven_meters": 0,
            "seven_meters_goals": 0
          },
          {
            "name": "Antoine Galy",
            "goals": 4,
            "two_min_penalties": 0,
            "yellow_cards": 0,
            "red_cards": 0,
            "blue_cards": 0,
            "seven_meters": 0,
            "seven_meters_goals": 0
          },
          {
            "name": "Luis Tempel Luque",
            "goals": 1,
            "two_min_penalties": 0,
            "yellow_cards": 0,
            "red_cards": 0,
            "blue_cards": 0,
            "seven_meters": 0,
            "seven_meters_goals": 0
          },
          {
            "name": "Alfons Stahl",
            "goals": 0,
            "two_min_penalties": 0,
            "yellow_cards": 0,
            "red_cards": 0,
            "blue_cards": 0,
            "seven_meters": 0,
            "seven_meters_goals": 0
          }
        ]
      },
      "away": {
        "team_name": "TSV Altensteig",
        "players": [
          {
            "name": "Jakob Leipersberger",
            "goals": 0,
            "two_min_penalties": 0,
            "yellow_cards": 0,
            "red_cards": 0,
            "blue_cards": 0,
            "seven_meters": 0,
            "seven_meters_goals": 0
          },
          {
            "name": "Frieder Fai\u00dft",
            "goals": 1,
            "two_min_penalties": 0,
            "yellow_cards": 0,
            "red_cards": 0,
            "blue_cards": 0,
            "seven_meters": 0,
            "seven_meters_goals": 0
          },
          {
            "name": "Tim Gedai",
            "goals": 2,
            "two_min_penalties": 1,
            "yellow_cards": 0,
            "red_cards": 0,
            "blue_cards": 0,
            "seven_meters": 0,
            "seven_meters_goals": 0
          },
          {
            "name": "Leonnis Morina",
            "goals": 1,
            "two_min_penalties": 2,
            "yellow_cards": 1,
            "red_cards": 0,
            "blue_cards": 0,
            "seven_meters": 0,
            "seven_meters_goals": 0
          },
          {
            "name": "Jannis Kalmbach",
            "goals": 3,
            "two_min_penalties": 0,
            "yellow_cards": 0,
            "red_cards": 0,
            "blue_cards": 0,
            "seven_meters": 0,
            "seven_meters_goals": 0
          },
          {
            "name": "Adriano Lacker",
            "goals": 1,
            "two_min_penalties": 0,
            "yellow_cards": 0,
            "red_cards": 0,
            "blue_cards": 0,
            "seven_meters": 0,
            "seven_meters_goals": 0
          },
          {
            "name": "Toni Armbruster",
            "goals": 0,
            "two_min_penalties": 1,
            "yellow_cards": 0,
            "red_cards": 0,
            "blue_cards": 0,
            "seven_meters": 0,
            "seven_meters_goals": 0
          },
          {
            "name": "Nick Z\u00fcfle",
            "goals": 5,
            "two_min_penalties": 0,
            "yellow_cards": 0,
            "red_cards": 0,
            "blue_cards": 0,
            "seven_meters": 2,
            "seven_meters_goals": 2
          },
          {
            "name": "Lorenz Dieterle",
            "goals": 0,
            "two_min_penalties": 0,
            "yellow_cards": 0,
            "red_cards": 0,
            "blue_cards": 0,
            "seven_meters": 0,
            "seven_meters_goals": 0
          },
          {
            "name": "Jannik Leipersberger",
            "goals": 2,
            "two_min_penalties": 1,
            "yellow_cards": 1,
            "red_cards": 0,
            "blue_cards": 0,
            "seven_meters": 0,
            "seven_meters_goals": 0
          },
          {
            "name": "Luis Fynn D\u00fcrr",
            "goals": 2,
            "two_min_penalties": 0,
            "yellow_cards": 0,
            "red_cards": 0,
            "blue_cards": 0,
            "seven_meters": 0,
            "seven_meters_goals": 0
          },
          {
            "name": "Frederik Digel",
            "goals": 1,
            "two_min_penalties": 0,
            "yellow_cards": 0,
            "red_cards": 0,
            "blue_cards": 0,
            "seven_meters": 0,
            "seven_meters_goals": 0
          },
          {
            "name": "Kian G\u00e4rtner",
            "goals": 0,
            "two_min_penalties": 0,
            "yellow_cards": 0,
            "red_cards": 0,
            "blue_cards": 0,
            "seven_meters": 0,
            "seven_meters_goals": 0
          },
          {
            "name": "Julius Hartmann",
            "goals": 0,
            "two_min_penalties": 0,
            "yellow_cards": 0,
            "red_cards": 0,
            "blue_cards": 0,
            "seven_meters": 0,
            "seven_meters_goals": 0
          },
          {
            "name": "Sam Raphael Angerer",
            "goals": 0,
            "two_min_penalties": 0,
            "yellow_cards": 0,
            "red_cards": 0,
            "blue_cards": 0,
            "seven_meters": 0,
            "seven_meters_goals": 0
          }
        ]
      },
      "goals_timeline": [
        {
          "minute": 0,
          "second": 25,
          "scorer": "Oskar Eder",
          "team": "home",
          "team_abbrev": "JSG Waldau",
          "seven_meter": false
        },
        {
          "minute": 0,
          "second": 52,
          "scorer": "Jannis Kalmbach",
          "team": "away",
          "team_abbrev": "TSV Altensteig",
          "seven_meter": false
        },
        {
          "minute": 1,
          "second": 18,
          "scorer": "Antoine Galy",
          "team": "home",
          "team_abbrev": "JSG Waldau",
          "seven_meter": false
        },
        {
          "minute": 1,
          "second": 42,
          "scorer": "Oskar Eder",
          "team": "home",
          "team_abbrev": "JSG Waldau",
          "seven_meter": false
        },
        {
          "minute": 2,
          "second": 12,
          "scorer": "Jannik Leipersberger",
          "team": "away",
          "team_abbrev": "TSV Altensteig",
          "seven_meter": false
        },
        {
          "minute": 3,
          "second": 46,
          "scorer": "Paul Schoewe",
          "team": "home",
          "team_abbrev": "JSG Waldau",
          "seven_meter": false
        },
        {
          "minute": 4,
          "second": 33,
          "scorer": "Nick Z\u00fcfle",
          "team": "away",
          "team_abbrev": "TSV Altensteig",
          "seven_meter": false
        },
        {
          "minute": 4,
          "second": 55,
          "scorer": "Oskar Eder",
          "team": "home",
          "team_abbrev": "JSG Waldau",
          "seven_meter": false
        },
        {
          "minute": 5,
          "second": 38,
          "scorer": "Jannis Kalmbach",
          "team": "away",
          "team_abbrev": "TSV Altensteig",
          "seven_meter": false
        },
        {
          "minute": 6,
          "second": 8,
          "scorer": "Oskar Eder",
          "team": "home",
          "team_abbrev": "JSG Waldau",
          "seven_meter": false
        },
        {
          "minute": 6,
          "second": 26,
          "scorer": "Nick Z\u00fcfle",
          "team": "away",
          "team_abbrev": "TSV Altensteig",
          "seven_meter": false
        },
        {
          "minute": 6,
          "second": 42,
          "scorer": "Antoine Galy",
          "team": "home",
          "team_abbrev": "JSG Waldau",
          "seven_meter": false
        },
        {
          "minute": 7,
          "second": 44,
          "scorer": "Adriano Lacker",
          "team": "away",
          "team_abbrev": "TSV Altensteig",
          "seven_meter": false
        },
        {
          "minute": 8,
          "second": 27,
          "scorer": "Tom Heldrich",
          "team": "home",
          "team_abbrev": "JSG Waldau",
          "seven_meter": false
        },
        {
          "minute": 9,
          "second": 53,
          "scorer": "Nick Z\u00fcfle",
          "team": "away",
          "team_abbrev": "TSV Altensteig",
          "seven_meter": true
        },
        {
          "minute": 10,
          "second": 43,
          "scorer": "Antoine Galy",
          "team": "home",
          "team_abbrev": "JSG Waldau",
          "seven_meter": false
        },
        {
          "minute": 11,
          "second": 16,
          "scorer": "Lukas Spitznagel",
          "team": "home",
          "team_abbrev": "JSG Waldau",
          "seven_meter": false
        },
        {
          "minute": 11,
          "second": 55,
          "scorer": "Antoine Galy",
          "team": "home",
          "team_abbrev": "JSG Waldau",
          "seven_meter": false
        },
        {
          "minute": 12,
          "second": 46,
          "scorer": "Paul Schoewe",
          "team": "home",
          "team_abbrev": "JSG Waldau",
          "seven_meter": false
        },
        {
          "minute": 14,
          "second": 2,
          "scorer": "Tom Heldrich",
          "team": "home",
          "team_abbrev": "JSG Waldau",
          "seven_meter": false
        },
        {
          "minute": 14,
          "second": 31,
          "scorer": "Luis D\u00fcrr",
          "team": "away",
          "team_abbrev": "TSV Altensteig",
          "seven_meter": false
        },
        {
          "minute": 15,
          "second": 40,
          "scorer": "Luis D\u00fcrr",
          "team": "away",
          "team_abbrev": "TSV Altensteig",
          "seven_meter": false
        },
        {
          "minute": 17,
          "second": 3,
          "scorer": "Tim Gedai",
          "team": "away",
          "team_abbrev": "TSV Altensteig",
          "seven_meter": false
        },
        {
          "minute": 17,
          "second": 26,
          "scorer": "Paul Schoewe",
          "team": "home",
          "team_abbrev": "JSG Waldau",
          "seven_meter": true
        },
        {
          "minute": 18,
          "second": 29,
          "scorer": "Paul Schoewe",
          "team": "home",
          "team_abbrev": "JSG Waldau",
          "seven_meter": false
        },
        {
          "minute": 19,
          "second": 11,
          "scorer": "Oskar Eder",
          "team": "home",
          "team_abbrev": "JSG Waldau",
          "seven_meter": false
        },
        {
          "minute": 19,
          "second": 51,
          "scorer": "Oskar Eder",
          "team": "home",
          "team_abbrev": "JSG Waldau",
          "seven_meter": false
        },
        {
          "minute": 21,
          "second": 5,
          "scorer": "Tom Heldrich",
          "team": "home",
          "team_abbrev": "JSG Waldau",
          "seven_meter": false
        },
        {
          "minute": 22,
          "second": 39,
          "scorer": "Leonnis Morina",
          "team": "away",
          "team_abbrev": "TSV Altensteig",
          "seven_meter": false
        },
        {
          "minute": 22,
          "second": 47,
          "scorer": "Tom Heldrich",
          "team": "home",
          "team_abbrev": "JSG Waldau",
          "seven_meter": false
        },
        {
          "minute": 23,
          "second": 51,
          "scorer": "Tom Heldrich",
          "team": "home",
          "team_abbrev": "JSG Waldau",
          "seven_meter": false
        },
        {
          "minute": 24,
          "second": 18,
          "scorer": "Luis Tempel Luque",
          "team": "home",
          "team_abbrev": "JSG Waldau",
          "seven_meter": false
        },
        {
          "minute": 26,
          "second": 25,
          "scorer": "Nick Z\u00fcfle",
          "team": "away",
          "team_abbrev": "TSV Altensteig",
          "seven_meter": true
        },
        {
          "minute": 27,
          "second": 2,
          "scorer": "Lukas Spitznagel",
          "team": "home",
          "team_abbrev": "JSG Waldau",
          "seven_meter": true
        },
        {
          "minute": 29,
          "second": 56,
          "scorer": "Adrian Hamm",
          "team": "home",
          "team_abbrev": "JSG Waldau",
          "seven_meter": false
        },
        {
          "minute": 30,
          "second": 27,
          "scorer": "Jannis Kalmbach",
          "team": "away",
          "team_abbrev": "TSV Altensteig",
          "seven_meter": false
        },
        {
          "minute": 30,
          "second": 50,
          "scorer": "Oskar Eder",
          "team": "home",
          "team_abbrev": "JSG Waldau",
          "seven_meter": false
        },
        {
          "minute": 31,
          "second": 59,
          "scorer": "Nick Z\u00fcfle",
          "team": "away",
          "team_abbrev": "TSV Altensteig",
          "seven_meter": false
        },
        {
          "minute": 32,
          "second": 42,
          "scorer": "Oskar Eder",
          "team": "home",
          "team_abbrev": "JSG Waldau",
          "seven_meter": false
        },
        {
          "minute": 33,
          "second": 30,
          "scorer": "Adrian Hamm",
          "team": "home",
          "team_abbrev": "JSG Waldau",
          "seven_meter": false
        },
        {
          "minute": 34,
          "second": 44,
          "scorer": "Oskar Eder",
          "team": "home",
          "team_abbrev": "JSG Waldau",
          "seven_meter": false
        },
        {
          "minute": 36,
          "second": 7,
          "scorer": "Paul Schoewe",
          "team": "home",
          "team_abbrev": "JSG Waldau",
          "seven_meter": false
        },
        {
          "minute": 38,
          "second": 1,
          "scorer": "Oskar Eder",
          "team": "home",
          "team_abbrev": "JSG Waldau",
          "seven_meter": false
        },
        {
          "minute": 38,
          "second": 26,
          "scorer": "Jannik Leipersberger",
          "team": "away",
          "team_abbrev": "TSV Altensteig",
          "seven_meter": false
        },
        {
          "minute": 39,
          "second": 13,
          "scorer": "Jonathan Thriemer",
          "team": "home",
          "team_abbrev": "JSG Waldau",
          "seven_meter": false
        },
        {
          "minute": 40,
          "second": 2,
          "scorer": "Oskar Eder",
          "team": "home",
          "team_abbrev": "JSG Waldau",
          "seven_meter": false
        },
        {
          "minute": 41,
          "second": 44,
          "scorer": "Frieder Fai\u00dft",
          "team": "away",
          "team_abbrev": "TSV Altensteig",
          "seven_meter": false
        },
        {
          "minute": 44,
          "second": 11,
          "scorer": "Lukas Spitznagel",
          "team": "home",
          "team_abbrev": "JSG Waldau",
          "seven_meter": false
        },
        {
          "minute": 45,
          "second": 1,
          "scorer": "Tim Gedai",
          "team": "away",
          "team_abbrev": "TSV Altensteig",
          "seven_meter": false
        },
        {
          "minute": 45,
          "second": 53,
          "scorer": "Paul Schoewe",
          "team": "home",
          "team_abbrev": "JSG Waldau",
          "seven_meter": false
        },
        {
          "minute": 46,
          "second": 44,
          "scorer": "Theo Fetzer",
          "team": "home",
          "team_abbrev": "JSG Waldau",
          "seven_meter": false
        },
        {
          "minute": 47,
          "second": 33,
          "scorer": "Frederik Digel",
          "team": "away",
          "team_abbrev": "TSV Altensteig",
          "seven_meter": false
        },
        {
          "minute": 48,
          "second": 20,
          "scorer": "Lukas Spitznagel",
          "team": "home",
          "team_abbrev": "JSG Waldau",
          "seven_meter": false
        }
      ],
      "final_score": "35:18",
      "half_duration": 30,
      "officials": {
        "referees": [
          "Fynn Stahl",
          "Paul Weing\u00e4rtner"
        ],
        "timekeepers": [
          "Kerim Ertugrul"
        ],
        "secretaries": [
          "Franz Angerer"
        ]
      },
      "graphic_path": "output/graphics/JSG_Stuttgart_Waldau_vs_TSV_Altensteig_So_3011.png"
    },
    {
      "game_id": "handball4all.baden-wuerttemberg.8666311",
      "order": 40,
      "date": "So, 30.11.",
      "home": {
        "team_name": "SG H2Ku Herrenberg",
        "players": [
          {
            "name": "Elia Rau",
            "goals": 0,
            "two_min_penalties": 0,
            "yellow_cards": 0,
            "red_cards": 0,
            "blue_cards": 0,
            "seven_meters": 0,
            "seven_meters_goals": 0
          },
          {
            "name": "Noah Baumg\u00e4rtner",
            "goals": 4,
            "two_min_penalties": 0,
            "yellow_cards": 0,
            "red_cards": 0,
            "blue_cards": 0,
            "seven_meters": 0,
            "seven_meters_goals": 0
          },
          {
            "name": "Mads Serwaty",
            "goals": 3,
            "two_min_penalties": 0,
            "yellow_cards": 0,
            "red_cards": 0,
            "blue_cards": 0,
            "seven_meters": 0,
            "seven_meters_goals": 0
          },
          {
            "name": "Gabriel Ferreira Alves",
            "goals": 2,
            "two_min_penalties": 0,
            "yellow_cards": 0,
            "red_cards": 0,
            "blue_cards": 0,
            "seven_meters": 0,
            "seven_meters_goals": 0
          },
          {
            "name": "Jakob Koimsidis",
            "goals": 2,
            "two_min_penalties": 1,
            "yellow_cards": 1,
            "red_cards": 0,
            "blue_cards": 0,
            "seven_meters": 0,
            "seven_meters_goals": 0
          },
          {
            "name": "Jonah Klose",
            "goals": 4,
            "two_min_penalties": 0,
            "yellow_cards": 0,
            "red_cards": 0,
            "blue_cards": 0,
            "seven_meters": 0,
            "seven_meters_goals": 0
          },
          {
            "name": "Julian Schuhmacher",
            "goals": 2,
            "two_min_penalties": 0,
            "yellow_cards": 0,
            "red_cards": 0,
            "blue_cards": 0,
            "seven_meters": 1,
            "seven_meters_goals": 1
          },
          {
            "name": "Kimi Brenner",
            "goals": 11,
            "two_min_penalties": 0,
            "yellow_cards": 0,
            "red_cards": 0,
            "blue_cards": 0,
            "seven_meters": 1,
            "seven_meters_goals": 1
          },
          {
            "name": "Bruno Schanbacher",
            "goals": 5,
            "two_min_penalties": 0,
            "yellow_cards": 0,
            "red_cards": 0,
            "blue_cards": 0,
            "seven_meters": 0,
            "seven_meters_goals": 0
          },
          {
            "name": "Tobias E\u00dflinger",
            "goals": 1,
            "two_min_penalties": 0,
            "yellow_cards": 0,
            "red_cards": 0,
            "blue_cards": 0,
            "seven_meters": 0,
            "seven_meters_goals": 0
          },
          {
            "name": "Nico Zimmer",
            "goals": 3,
            "two_min_penalties": 1,
            "yellow_cards": 0,
            "red_cards": 0,
            "blue_cards": 0,
            "seven_meters": 0,
            "seven_meters_goals": 0
          },
          {
            "name": "Lasse Stahl",
            "goals": 4,
            "two_min_penalties": 2,
            "yellow_cards": 0,
            "red_cards": 0,
            "blue_cards": 0,
            "seven_meters": 0,
            "seven_meters_goals": 0
          },
          {
            "name": "Emilian Schmid",
            "goals": 3,
            "two_min_penalties": 0,
            "yellow_cards": 0,
            "red_cards": 0,
            "blue_cards": 0,
            "seven_meters": 0,
            "seven_meters_goals": 0
          },
          {
            "name": "Anton Zolg",
            "goals": 0,
            "two_min_penalties": 0,
            "yellow_cards": 0,
            "red_cards": 0,
            "blue_cards": 0,
            "seven_meters": 0,
            "seven_meters_goals": 0
          }
        ]
      },
      "away": {
        "team_name": "HSC Schmiden/Oeffingen 2004",
        "players": [
          {
            "name": "Maximilian Knapp",
            "goals": 4,
            "two_min_penalties": 0,
            "yellow_cards": 0,
            "red_cards": 0,
            "blue_cards": 0,
            "seven_meters": 3,
            "seven_meters_goals": 1
          },
          {
            "name": "Luca Blind",
            "goals": 7,
            "two_min_penalties": 0,
            "yellow_cards": 0,
            "red_cards": 0,
            "blue_cards": 0,
            "seven_meters": 0,
            "seven_meters_goals": 0
          },
          {
            "name": "Frederik Hampel",
            "goals": 0,
            "two_min_penalties": 0,
            "yellow_cards": 0,
            "red_cards": 0,
            "blue_cards": 0,
            "seven_meters": 0,
            "seven_meters_goals": 0
          },
          {
            "name": "Simon Rothwein",
            "goals": 1,
            "two_min_penalties": 0,
            "yellow_cards": 0,
            "red_cards": 0,
            "blue_cards": 0,
            "seven_meters": 0,
            "seven_meters_goals": 0
          },
          {
            "name": "Christian Koch",
            "goals": 7,
            "two_min_penalties": 0,
            "yellow_cards": 0,
            "red_cards": 0,
            "blue_cards": 0,
            "seven_meters": 0,
            "seven_meters_goals": 0
          },
          {
            "name": "Philipp Gro\u00df",
            "goals": 1,
            "two_min_penalties": 0,
            "yellow_cards": 0,
            "red_cards": 0,
            "blue_cards": 0,
            "seven_meters": 0,
            "seven_meters_goals": 0
          },
          {
            "name": "Robin Kursawe",
            "goals": 0,
            "two_min_penalties": 0,
            "yellow_cards": 0,
            "red_cards": 0,
            "blue_cards": 0,
            "seven_meters": 0,
            "seven_meters_goals": 0
          },
          {
            "name": "Eliah Amort",
            "goals": 2,
            "two_min_penalties": 0,
            "yellow_cards": 0,
            "red_cards": 0,
            "blue_cards": 0,
            "seven_meters": 0,
            "seven_meters_goals": 0
          },
          {
            "name": "Leonas Johann Renz",
            "goals": 10,
            "two_min_penalties": 0,
            "yellow_cards": 0,
            "red_cards": 0,
            "blue_cards": 0,
            "seven_meters": 0,
            "seven_meters_goals": 0
          },
          {
            "name": "Benjamin Hess",
            "goals": 3,
            "two_min_penalties": 0,
            "yellow_cards": 0,
            "red_cards": 0,
            "blue_cards": 0,
            "seven_meters": 0,
            "seven_meters_goals": 0
          },
          {
            "name": "Collin Pohl",
            "goals": 0,
            "two_min_penalties": 0,
            "yellow_cards": 0,
            "red_cards": 0,
            "blue_cards": 0,
            "seven_meters": 0,
            "seven_meters_goals": 0
          }
        ]
      },
      "goals_timeline": [
        {
          "minute": 1,
          "second": 13,
          "scorer": "Kimi Brenner",
          "team": "home",
          "team_abbrev": "H2Ku Herrenb.",
          "seven_meter": false
        },
        {
          "minute": 1,
          "second": 34,
          "scorer": "Luca Blind",
          "team": "away",
          "team_abbrev": "HSC Schm/Oeff",
          "seven_meter": false
        },
        {
          "minute": 2,
          "second": 5,
          "scorer": "Noah Baumg\u00e4rtner",
          "team": "home",
          "team_abbrev": "H2Ku Herrenb.",
          "seven_meter": false
        },
        {
          "minute": 3,
          "second": 38,
          "scorer": "Jonah Klose",
          "team": "home",
          "team_abbrev": "H2Ku Herrenb.",
          "seven_meter": false
        },
        {
          "minute": 4,
          "second": 49,
          "scorer": "Kimi Brenner",
          "team": "home",
          "team_abbrev": "H2Ku Herrenb.",
          "seven_meter": false
        },
        {
          "minute": 5,
          "second": 39,
          "scorer": "Kimi Brenner",
          "team": "home",
          "team_abbrev": "H2Ku Herrenb.",
          "seven_meter": true
        },
        {
          "minute": 6,
          "second": 6,
          "scorer": "Eliah Amort",
          "team": "away",
          "team_abbrev": "HSC Schm/Oeff",
          "seven_meter": false
        },
        {
          "minute": 6,
          "second": 41,
          "scorer": "Nico Zimmer",
          "team": "home",
          "team_abbrev": "H2Ku Herrenb.",
          "seven_meter": false
        },
        {
          "minute": 7,
          "second": 8,
          "scorer": "Eliah Amort",
          "team": "away",
          "team_abbrev": "HSC Schm/Oeff",
          "seven_meter": false
        },
        {
          "minute": 7,
          "second": 19,
          "scorer": "Jonah Klose",
          "team": "home",
          "team_abbrev": "H2Ku Herrenb.",
          "seven_meter": false
        },
        {
          "minute": 7,
          "second": 48,
          "scorer": "Leonas Renz",
          "team": "away",
          "team_abbrev": "HSC Schm/Oeff",
          "seven_meter": false
        },
        {
          "minute": 7,
          "second": 57,
          "scorer": "Kimi Brenner",
          "team": "home",
          "team_abbrev": "H2Ku Herrenb.",
          "seven_meter": false
        },
        {
          "minute": 8,
          "second": 8,
          "scorer": "Nico Zimmer",
          "team": "home",
          "team_abbrev": "H2Ku Herrenb.",
          "seven_meter": false
        },
        {
          "minute": 8,
          "second": 29,
          "scorer": "Luca Blind",
          "team": "away",
          "team_abbrev": "HSC Schm/Oeff",
          "seven_meter": false
        },
        {
          "minute": 9,
          "second": 48,
          "scorer": "Kimi Brenner",
          "team": "home",
          "team_abbrev": "H2Ku Herrenb.",
          "seven_meter": false
        },
        {
          "minute": 10,
          "second": 15,
          "scorer": "Tobias E\u00dflinger",
          "team": "home",
          "team_abbrev": "H2Ku Herrenb.",
          "seven_meter": false
        },
        {
          "minute": 11,
          "second": 13,
          "scorer": "Jonah Klose",
          "team": "home",
          "team_abbrev": "H2Ku Herrenb.",
          "seven_meter": false
        },
        {
          "minute": 11,
          "second": 41,
          "scorer": "Kimi Brenner",
          "team": "home",
          "team_abbrev": "H2Ku Herrenb.",
          "seven_meter": false
        },
        {
          "minute": 12,
          "second": 20,
          "scorer": "Christian Koch",
          "team": "away",
          "team_abbrev": "HSC Schm/Oeff",
          "seven_meter": false
        },
        {
          "minute": 12,
          "second": 32,
          "scorer": "Jakob Koimsidis",
          "team": "home",
          "team_abbrev": "H2Ku Herrenb.",
          "seven_meter": false
        },
        {
          "minute": 12,
          "second": 46,
          "scorer": "Luca Blind",
          "team": "away",
          "team_abbrev": "HSC Schm/Oeff",
          "seven_meter": false
        },
        {
          "minute": 12,
          "second": 56,
          "scorer": "Kimi Brenner",
          "team": "home",
          "team_abbrev": "H2Ku Herrenb.",
          "seven_meter": false
        },
        {
          "minute": 13,
          "second": 58,
          "scorer": "Noah Baumg\u00e4rtner",
          "team": "home",
          "team_abbrev": "H2Ku Herrenb.",
          "seven_meter": false
        },
        {
          "minute": 14,
          "second": 45,
          "scorer": "Leonas Renz",
          "team": "away",
          "team_abbrev": "HSC Schm/Oeff",
          "seven_meter": true
        },
        {
          "minute": 15,
          "second": 43,
          "scorer": "Kimi Brenner",
          "team": "home",
          "team_abbrev": "H2Ku Herrenb.",
          "seven_meter": false
        },
        {
          "minute": 16,
          "second": 45,
          "scorer": "Luca Blind",
          "team": "away",
          "team_abbrev": "HSC Schm/Oeff",
          "seven_meter": false
        },
        {
          "minute": 16,
          "second": 55,
          "scorer": "Emilian Schmid",
          "team": "home",
          "team_abbrev": "H2Ku Herrenb.",
          "seven_meter": false
        },
        {
          "minute": 17,
          "second": 27,
          "scorer": "Maximilian Knapp",
          "team": "away",
          "team_abbrev": "HSC Schm/Oeff",
          "seven_meter": false
        },
        {
          "minute": 17,
          "second": 55,
          "scorer": "Emilian Schmid",
          "team": "home",
          "team_abbrev": "H2Ku Herrenb.",
          "seven_meter": false
        },
        {
          "minute": 18,
          "second": 36,
          "scorer": "Mads Serwaty",
          "team": "home",
          "team_abbrev": "H2Ku Herrenb.",
          "seven_meter": false
        },
        {
          "minute": 19,
          "second": 31,
          "scorer": "Maximilian Knapp",
          "team": "away",
          "team_abbrev": "HSC Schm/Oeff",
          "seven_meter": true
        },
        {
          "minute": 20,
          "second": 5,
          "scorer": "Luca Blind",
          "team": "away",
          "team_abbrev": "HSC Schm/Oeff",
          "seven_meter": false
        },
        {
          "minute": 20,
          "second": 54,
          "scorer": "Julian Schuhmacher",
          "team": "home",
          "team_abbrev": "H2Ku Herrenb.",
          "seven_meter": false
        },
        {
          "minute": 21,
          "second": 11,
          "scorer": "Leonas Renz",
          "team": "away",
          "team_abbrev": "HSC Schm/Oeff",
          "seven_meter": false
        },
        {
          "minute": 21,
          "second": 29,
          "scorer": "Emilian Schmid",
          "team": "home",
          "team_abbrev": "H2Ku Herrenb.",
          "seven_meter": false
        },
        {
          "minute": 22,
          "second": 4,
          "scorer": "Christian Koch",
          "team": "away",
          "team_abbrev": "HSC Schm/Oeff",
          "seven_meter": false
        },
        {
          "minute": 22,
          "second": 37,
          "scorer": "Bruno Schanbacher",
          "team": "home",
          "team_abbrev": "H2Ku Herrenb.",
          "seven_meter": false
        },
        {
          "minute": 24,
          "second": 9,
          "scorer": "Leonas Renz",
          "team": "away",
          "team_abbrev": "HSC Schm/Oeff",
          "seven_meter": false
        },
        {
          "minute": 25,
          "second": 0,
          "scorer": "Jakob Koimsidis",
          "team": "home",
          "team_abbrev": "H2Ku Herrenb.",
          "seven_meter": false
        },
        {
          "minute": 25,
          "second": 30,
          "scorer": "Bruno Schanbacher",
          "team": "home",
          "team_abbrev": "H2Ku Herrenb.",
          "seven_meter": false
        },
        {
          "minute": 25,
          "second": 42,
          "scorer": "Leonas Renz",
          "team": "away",
          "team_abbrev": "HSC Schm/Oeff",
          "seven_meter": false
        },
        {
          "minute": 26,
          "second": 7,
          "scorer": "Christian Koch",
          "team": "away",
          "team_abbrev": "HSC Schm/Oeff",
          "seven_meter": false
        },
        {
          "minute": 26,
          "second": 16,
          "scorer": "Kimi Brenner",
          "team": "home",
          "team_abbrev": "H2Ku Herrenb.",
          "seven_meter": false
        },
        {
          "minute": 26,
          "second": 58,
          "scorer": "Bruno Schanbacher",
          "team": "home",
          "team_abbrev": "H2Ku Herrenb.",
          "seven_meter": false
        },
        {
          "minute": 27,
          "second": 58,
          "scorer": "Kimi Brenner",
          "team": "home",
          "team_abbrev": "H2Ku Herrenb.",
          "seven_meter": false
        },
        {
          "minute": 28,
          "second": 31,
          "scorer": "Luca Blind",
          "team": "away",
          "team_abbrev": "HSC Schm/Oeff",
          "seven_meter": false
        },
        {
          "minute": 28,
          "second": 42,
          "scorer": "Lasse Stahl",
          "team": "home",
          "team_abbrev": "H2Ku Herrenb.",
          "seven_meter": false
        },
        {
          "minute": 29,
          "second": 22,
          "scorer": "Bruno Schanbacher",
          "team": "home",
          "team_abbrev": "H2Ku Herrenb.",
          "seven_meter": false
        },
        {
          "minute": 29,
          "second": 43,
          "scorer": "Christian Koch",
          "team": "away",
          "team_abbrev": "HSC Schm/Oeff",
          "seven_meter": false
        },
        {
          "minute": 29,
          "second": 53,
          "scorer": "Mads Serwaty",
          "team": "home",
          "team_abbrev": "H2Ku Herrenb.",
          "seven_meter": false
        },
        {
          "minute": 30,
          "second": 24,
          "scorer": "Leonas Renz",
          "team": "away",
          "team_abbrev": "HSC Schm/Oeff",
          "seven_meter": false
        },
        {
          "minute": 30,
          "second": 49,
          "scorer": "Kimi Brenner",
          "team": "home",
          "team_abbrev": "H2Ku Herrenb.",
          "seven_meter": false
        },
        {
          "minute": 32,
          "second": 33,
          "scorer": "Gabriel Ferreira Alves",
          "team": "home",
          "team_abbrev": "H2Ku Herrenb.",
          "seven_meter": false
        },
        {
          "minute": 33,
          "second": 6,
          "scorer": "Christian Koch",
          "team": "away",
          "team_abbrev": "HSC Schm/Oeff",
          "seven_meter": false
        },
        {
          "minute": 34,
          "second": 9,
          "scorer": "Benjamin Hess",
          "team": "away",
          "team_abbrev": "HSC Schm/Oeff",
          "seven_meter": false
        },
        {
          "minute": 34,
          "second": 43,
          "scorer": "Christian Koch",
          "team": "away",
          "team_abbrev": "HSC Schm/Oeff",
          "seven_meter": false
        },
        {
          "minute": 35,
          "second": 8,
          "scorer": "Bruno Schanbacher",
          "team": "home",
          "team_abbrev": "H2Ku Herrenb.",
          "seven_meter": false
        },
        {
          "minute": 35,
          "second": 24,
          "scorer": "Christian Koch",
          "team": "away",
          "team_abbrev": "HSC Schm/Oeff",
          "seven_meter": false
        },
        {
          "minute": 35,
          "second": 52,
          "scorer": "Lasse Stahl",
          "team": "home",
          "team_abbrev": "H2Ku Herrenb.",
          "seven_meter": false
        },
        {
          "minute": 37,
          "second": 43,
          "scorer": "Simon Rothwein",
          "team": "away",
          "team_abbrev": "HSC Schm/Oeff",
          "seven_meter": false
        },
        {
          "minute": 38,
          "second": 9,
          "scorer": "Gabriel Ferreira Alves",
          "team": "home",
          "team_abbrev": "H2Ku Herrenb.",
          "seven_meter": false
        },
        {
          "minute": 38,
          "second": 31,
          "scorer": "Benjamin Hess",
          "team": "away",
          "team_abbrev": "HSC Schm/Oeff",
          "seven_meter": false
        },
        {
          "minute": 39,
          "second": 5,
          "scorer": "Mads Serwaty",
          "team": "home",
          "team_abbrev": "H2Ku Herrenb.",
          "seven_meter": false
        },
        {
          "minute": 39,
          "second": 21,
          "scorer": "Maximilian Knapp",
          "team": "away",
          "team_abbrev": "HSC Schm/Oeff",
          "seven_meter": false
        },
        {
          "minute": 40,
          "second": 2,
          "scorer": "Julian Schuhmacher",
          "team": "home",
          "team_abbrev": "H2Ku Herrenb.",
          "seven_meter": true
        },
        {
          "minute": 40,
          "second": 53,
          "scorer": "Luca Blind",
          "team": "away",
          "team_abbrev": "HSC Schm/Oeff",
          "seven_meter": false
        },
        {
          "minute": 42,
          "second": 43,
          "scorer": "Nico Zimmer",
          "team": "home",
          "team_abbrev": "H2Ku Herrenb.",
          "seven_meter": false
        },
        {
          "minute": 43,
          "second": 29,
          "scorer": "Leonas Renz",
          "team": "away",
          "team_abbrev": "HSC Schm/Oeff",
          "seven_meter": true
        },
        {
          "minute": 44,
          "second": 15,
          "scorer": "Jonah Klose",
          "team": "home",
          "team_abbrev": "H2Ku Herrenb.",
          "seven_meter": false
        },
        {
          "minute": 44,
          "second": 38,
          "scorer": "Philipp Gro\u00df",
          "team": "away",
          "team_abbrev": "HSC Schm/Oeff",
          "seven_meter": false
        },
        {
          "minute": 45,
          "second": 2,
          "scorer": "Leonas Renz",
          "team": "away",
          "team_abbrev": "HSC Schm/Oeff",
          "seven_meter": false
        },
        {
          "minute": 46,
          "second": 10,
          "scorer": "Noah Baumg\u00e4rtner",
          "team": "home",
          "team_abbrev": "H2Ku Herrenb.",
          "seven_meter": false
        },
        {
          "minute": 46,
          "second": 39,
          "scorer": "Leonas Renz",
          "team": "away",
          "team_abbrev": "HSC Schm/Oeff",
          "seven_meter": false
        },
        {
          "minute": 47,
          "second": 12,
          "scorer": "Lasse Stahl",
          "team": "home",
          "team_abbrev": "H2Ku Herrenb.",
          "seven_meter": false
        },
        {
          "minute": 47,
          "second": 39,
          "scorer": "Maximilian Knapp",
          "team": "away",
          "team_abbrev": "HSC Schm/Oeff",
          "seven_meter": false
        },
        {
          "minute": 48,
          "second": 19,
          "scorer": "Noah Baumg\u00e4rtner",
          "team": "home",
          "team_abbrev": "H2Ku Herrenb.",
          "seven_meter": false
        },
        {
          "minute": 48,
          "second": 28,
          "scorer": "Leonas Renz",
          "team": "away",
          "team_abbrev": "HSC Schm/Oeff",
          "seven_meter": true
        },
        {
          "minute": 48,
          "second": 54,
          "scorer": "Lasse Stahl",
          "team": "home",
          "team_abbrev": "H2Ku Herrenb.",
          "seven_meter": false
        },
        {
          "minute": 49,
          "second": 11,
          "scorer": "Benjamin Hess",
          "team": "away",
          "team_abbrev": "HSC Schm/Oeff",
          "seven_meter": false
        }
      ],
      "final_score": "44:35",
      "half_duration": 30,
      "officials": {
        "referees": [
          "Kaan Ertugrul",
          "Haris Osmanagic"
        ],
        "timekeepers": [
          "Ulrike Zimmer"
        ],
        "secretaries": [
          "Alexander Renz"
        ]
      },
      "graphic_path": "output/graphics/SG_H2Ku_Herrenberg_vs_HSC_Schmiden_Oeffing_So_3011.png"
    }
  ]
}